spark_master_rest_api
