Metadata-Version: 2.1
Name: spark-master-rest-api
Version: 0.1.2
Summary: Wrapper for spark master REST API
Home-page: https://github.com/nazerpanahi/spark-master-rest-api
Author: Hamid Nazerpanahi
License: GPLv3
Classifier: Programming Language :: Python :: 3
Classifier: Operating System :: OS Independent
Requires-Python: >=3.6
License-File: LICENSE
